witty.py
witty_cli-0.0.3.dist-info/DESCRIPTION.rst
witty_cli-0.0.3.dist-info/METADATA
witty_cli-0.0.3.dist-info/RECORD
witty_cli-0.0.3.dist-info/WHEEL
witty_cli-0.0.3.dist-info/entry_points.txt
witty_cli-0.0.3.dist-info/metadata.json
witty_cli-0.0.3.dist-info/top_level.txt
